genie3/__init__.py
genie3/config.py
genie3/eval.py
genie3/genie3.py
genie3/plot.py
genie3/utils.py
genie3/data/__init__.py
genie3/data/dataset.py
genie3/data/loading.py
genie3/data/utils.py
genie3/regressor/__init__.py
genie3/regressor/extratrees.py
genie3/regressor/lightgbm.py
genie3/regressor/protocol.py
genie3/regressor/randomforest.py
genie3/regressor/xgboost.py
genie3-0.1.0.dist-info/METADATA
genie3-0.1.0.dist-info/WHEEL
genie3-0.1.0.dist-info/RECORD
