Metadata-Version: 2.4
Name: genie3
Version: 0.1.0
Summary: An implementation of GENIE3.
Classifier: Development Status :: 3 - Alpha
Classifier: Environment :: Console
Classifier: Intended Audience :: Developers
Classifier: Intended Audience :: Education
Classifier: Intended Audience :: Science/Research
Classifier: License :: OSI Approved :: MIT License
Classifier: Programming Language :: Python :: 3
Classifier: Programming Language :: Python :: 3.12
Requires-Python: ==3.12.*
Requires-Dist: lightgbm>=4.5.0
Requires-Dist: numpy>=1.26.4
Requires-Dist: pandas[performance]~=2.2.3
Requires-Dist: pydantic>=2.10.4
Requires-Dist: pyyaml>=6.0.2
Requires-Dist: scikit-learn~=1.5.2
Requires-Dist: seaborn>=0.13.2
Requires-Dist: tqdm>=4.67.0
Requires-Dist: typer~=0.12.5
Requires-Dist: xgboost>=2.1.3
